LICENSE.txt
MANIFEST.in
changelog.md
collaborators.md
readme.md
setup.cfg
setup.py
django_gas.egg-info/PKG-INFO
django_gas.egg-info/SOURCES.txt
django_gas.egg-info/dependency_links.txt
django_gas.egg-info/top_level.txt
gas/__init__.py
gas/admin.py
gas/apps.py
gas/forms.py
gas/gas_settings.py
gas/models.py
gas/sites.py
gas/utils.py
gas/views.py
gas/gas/__init__.py
gas/gas/config.py
gas/gas/users_config.py
gas/gas/core/__init__.py
gas/gas/core/urls.py
gas/gas/core/views.py
gas/gas/users/__init__.py
gas/gas/users/forms.py
gas/gas/users/urls.py
gas/gas/users/views.py
gas/locale/es/LC_MESSAGES/django.mo
gas/locale/es/LC_MESSAGES/django.po
gas/locale/eu/LC_MESSAGES/django.mo
gas/locale/eu/LC_MESSAGES/django.po
gas/migrations/0001_initial.py
gas/migrations/__init__.py
gas/static/gas/css/gas.css
gas/static/gas/css/img/logo.svg
gas/static/gas/js/add_popups.js
gas/static/gas/js/gas.js
gas/static/vendor/jquery-3.6.4.min.js
gas/static/vendor/jquery.formset.js
gas/static/vendor/font-awesome/LICENSE.txt
gas/static/vendor/font-awesome/css/all.css
gas/static/vendor/font-awesome/css/all.min.css
gas/static/vendor/font-awesome/css/brands.css
gas/static/vendor/font-awesome/css/brands.min.css
gas/static/vendor/font-awesome/css/fontawesome.css
gas/static/vendor/font-awesome/css/fontawesome.min.css
gas/static/vendor/font-awesome/css/regular.css
gas/static/vendor/font-awesome/css/regular.min.css
gas/static/vendor/font-awesome/css/solid.css
gas/static/vendor/font-awesome/css/solid.min.css
gas/static/vendor/font-awesome/css/svg-with-js.css
gas/static/vendor/font-awesome/css/svg-with-js.min.css
gas/static/vendor/font-awesome/css/v4-shims.css
gas/static/vendor/font-awesome/css/v4-shims.min.css
gas/static/vendor/font-awesome/js/all.js
gas/static/vendor/font-awesome/js/all.min.js
gas/static/vendor/font-awesome/js/brands.js
gas/static/vendor/font-awesome/js/brands.min.js
gas/static/vendor/font-awesome/js/conflict-detection.js
gas/static/vendor/font-awesome/js/conflict-detection.min.js
gas/static/vendor/font-awesome/js/fontawesome.js
gas/static/vendor/font-awesome/js/fontawesome.min.js
gas/static/vendor/font-awesome/js/regular.js
